{
  "specs": {
    "interactions": {
      "current_version": "v1beta",
      "last_fetched": "2026-05-06T16:25:43.341974Z",
      "source_url": "https://ai.google.dev/static/api/interactions.openapi.json",
      "title": "Gemini API",
      "version_history": []
    },
    "main": {
      "current_version": "v1beta",
      "last_fetched": "2026-05-06T16:25:42.194568Z",
      "source_url": "https://generativelanguage.googleapis.com/$discovery/OPENAPI3_0?version=v1beta",
      "title": "Gemini API",
      "version_history": []
    }
  }
}
